solverpy/__init__.py
solverpy/benchmark/__init__.py
solverpy/benchmark/evaluation.py
solverpy/benchmark/summary.py
solverpy/benchmark/db/__init__.py
solverpy/benchmark/db/cachedprovider.py
solverpy/benchmark/db/db.py
solverpy/benchmark/db/provider.py
solverpy/benchmark/db/providers/__init__.py
solverpy/benchmark/db/providers/jsons.py
solverpy/benchmark/db/providers/loader.py
solverpy/benchmark/db/providers/solved.py
solverpy/benchmark/db/providers/status.py
solverpy/benchmark/path/__init__.py
solverpy/benchmark/path/bids.py
solverpy/benchmark/path/sids.py
solverpy/benchmark/reports/__init__.py
solverpy/benchmark/reports/data.py
solverpy/benchmark/reports/markdown.py
solverpy/benchmark/reports/progress.py
solverpy/builder/__init__.py
solverpy/builder/autotuner.py
solverpy/builder/builder.py
solverpy/builder/cvc5ml.py
solverpy/builder/enigma.py
solverpy/builder/svm.py
solverpy/builder/autotune/__init__.py
solverpy/builder/autotune/autotune.py
solverpy/builder/autotune/build.py
solverpy/builder/autotune/check.py
solverpy/builder/autotune/listener.py
solverpy/builder/autotune/tune.py
solverpy/builder/plugins/__init__.py
solverpy/builder/plugins/cvc5.py
solverpy/builder/plugins/enigma.py
solverpy/builder/plugins/multi.py
solverpy/builder/plugins/svm.py
solverpy/builder/plugins/trains.py
solverpy/setups/__init__.py
solverpy/setups/common.py
solverpy/setups/loop.py
solverpy/setups/setup.py
solverpy/setups/solver.py
solverpy/setups/tuner.py
solverpy/solver/__init__.py
solverpy/solver/object.py
solverpy/solver/pluginsolver.py
solverpy/solver/reloader.py
solverpy/solver/shellsolver.py
solverpy/solver/solver.py
solverpy/solver/solverpy.py
solverpy/solver/stdinsolver.py
solverpy/solver/atp/__init__.py
solverpy/solver/atp/cvc5.py
solverpy/solver/atp/eprover.py
solverpy/solver/atp/lash.py
solverpy/solver/atp/prover9.py
solverpy/solver/atp/vampire.py
solverpy/solver/plugins/__init__.py
solverpy/solver/plugins/decorator.py
solverpy/solver/plugins/plugin.py
solverpy-1.9.2.dist-info/licenses/LICENSE
solverpy-1.9.2.dist-info/METADATA
solverpy-1.9.2.dist-info/WHEEL
solverpy-1.9.2.dist-info/top_level.txt
solverpy-1.9.2.dist-info/RECORD
